README.rst
setup.py
mplane/__init__.py
mplane/azn.py
mplane/client.py
mplane/component.py
mplane/model.py
mplane/registry.json
mplane/scheduler.py
mplane/supervisor.py
mplane/tests.py
mplane/tls.py
mplane/utils.py
mplane/components/example.py
mplane/components/loopback.py
mplane/components/ping.py
mplane_sdk.egg-info/PKG-INFO
mplane_sdk.egg-info/SOURCES.txt
mplane_sdk.egg-info/dependency_links.txt
mplane_sdk.egg-info/requires.txt
mplane_sdk.egg-info/top_level.txt
scripts/mpcli
scripts/mpcom
scripts/mpsup