Metadata-Version: 1.1
Name: mplane-sdk
Version: 0.9.0
Summary: mPlane Software Development Kit for Python 3
Home-page: http://github.com/fp7mplane/protocol-ri
Author: Brian Trammell
Author-email: brian@trammell.ch
License: UNKNOWN
Platform: UNKNOWN
Classifier: Development Status :: 3 - Alpha
Classifier: Intended Audience :: Developers
Classifier: License :: OSI Approved :: GNU Lesser General Public License v3 or later (LGPLv3+)
Classifier: Operating System :: OS Independent
Classifier: Programming Language :: Python :: 3.3
Classifier: Topic :: System :: Networking
